<annotation>
	<folder>Expressions Data</folder>
	<filename>Screen Shot 2020-07-23 at 9.49.40 PM.png</filename>
	<path>/Users/jeremiahliao/Desktop/Expressions Data/Screen Shot 2020-07-23 at 9.49.40 PM.png</path>
	<source>
		<database>Unknown</database>
	</source>
	<size>
		<width>2880</width>
		<height>1800</height>
		<depth>3</depth>
	</size>
	<segmented>0</segmented>
	<object>
		<name>happy</name>
		<pose>Unspecified</pose>
		<truncated>0</truncated>
		<difficult>0</difficult>
		<bndbox>
			<xmin>1972</xmin>
			<ymin>140</ymin>
			<xmax>2358</xmax>
			<ymax>715</ymax>
		</bndbox>
	</object>
</annotation>
