<annotation>
	<folder>Expressions Data</folder>
	<filename>Screen Shot 2020-08-06 at 2.43.23 PM.png</filename>
	<path>/Users/jeremiahliao/Desktop/Expressions Data/Screen Shot 2020-08-06 at 2.43.23 PM.png</path>
	<source>
		<database>Unknown</database>
	</source>
	<size>
		<width>2880</width>
		<height>1800</height>
		<depth>3</depth>
	</size>
	<segmented>0</segmented>
	<object>
		<name>sad</name>
		<pose>Unspecified</pose>
		<truncated>0</truncated>
		<difficult>0</difficult>
		<bndbox>
			<xmin>361</xmin>
			<ymin>688</ymin>
			<xmax>527</xmax>
			<ymax>888</ymax>
		</bndbox>
	</object>
	<object>
		<name>sad</name>
		<pose>Unspecified</pose>
		<truncated>0</truncated>
		<difficult>0</difficult>
		<bndbox>
			<xmin>127</xmin>
			<ymin>716</ymin>
			<xmax>266</xmax>
			<ymax>894</ymax>
		</bndbox>
	</object>
	<object>
		<name>sad</name>
		<pose>Unspecified</pose>
		<truncated>0</truncated>
		<difficult>0</difficult>
		<bndbox>
			<xmin>1849</xmin>
			<ymin>483</ymin>
			<xmax>2063</xmax>
			<ymax>811</ymax>
		</bndbox>
	</object>
	<object>
		<name>sad</name>
		<pose>Unspecified</pose>
		<truncated>0</truncated>
		<difficult>0</difficult>
		<bndbox>
			<xmin>1469</xmin>
			<ymin>569</ymin>
			<xmax>1702</xmax>
			<ymax>880</ymax>
		</bndbox>
	</object>
</annotation>
